wzlight/__init__.py
wzlight/api.py
wzlight/client.py
wzlight/enums.py
wzlight-0.1.33.dist-info/WHEEL
wzlight-0.1.33.dist-info/METADATA
wzlight-0.1.33.dist-info/RECORD
