Metadata-Version: 2.1
Name: wzlight
Version: 0.1.33
Summary: Light asynchronous wrapper for COD Warzone API
Home-page: https://github.com/matthieuvion/wzlight
License: MIT
Keywords: warzone,API,asynchronous,httpx
Author: Matthieu Vion
Author-email: viomatthieu@gmail.com
Requires-Python: >=3.9,<4.0
Classifier: License :: OSI Approved :: MIT License
Classifier: Programming Language :: Python :: 3
Classifier: Programming Language :: Python :: 3.10
Classifier: Programming Language :: Python :: 3.9
Requires-Dist: async-lru (>=1.0.3,<2.0.0)
Requires-Dist: backoff (>=2.1.2,<3.0.0)
Requires-Dist: httpx[http2] (>=0.23.0,<0.24.0)
Requires-Dist: jupyterlab (>=3.4.3,<4.0.0)
Requires-Dist: python-dotenv (>=0.19.0,<0.20.0)
Project-URL: Repository, https://github.com/matthieuvion/wzlight
